botodom/__init__.py
botodom/scripts/__init__.py
botodom/user.py
botodom-0.1.0.dist-info/entry_points.txt
botodom-0.1.0.dist-info/METADATA
botodom-0.1.0.dist-info/WHEEL
botodom-0.1.0.dist-info/RECORD
